LICENSE
MANIFEST.in
README.rst
VERSION
makechat.conf
setup.py
docs/Makefile
docs/conf.py
docs/index.rst
docs/installation.rst
docs/management.rst
docs/upgrade.rst
docs/api/index.rst
docs/api/endpoints/members.rst
docs/api/endpoints/messages.rst
docs/api/endpoints/rooms.rst
docs/makechat/index.rst
docs/makechat/api/index.rst
makechat.egg-info/PKG-INFO
makechat.egg-info/SOURCES.txt
makechat.egg-info/dependency_links.txt
makechat.egg-info/entry_points.txt
makechat.egg-info/requires.txt
makechat.egg-info/top_level.txt
src/__init__.py
src/manage.py
src/models.py
src/api/__init__.py
src/api/hooks.py
src/api/members.py
src/api/messages.py
src/api/middlewares.py
src/api/rooms.py
src/api/tokens.py
src/api/users.py
src/api/utils.py