Metadata-Version: 1.1
Name: makechat
Version: 0.1.22
Summary: Simple chat system
Home-page: http://makechat.tk
Author: Andrew Burdyug
Author-email: buran83@gmail.com
License: Apache License, Version 2.0
Keywords: chat
Platform: UNKNOWN
Classifier: Development Status :: 3 - Alpha
Classifier: Intended Audience :: Developers
Classifier: Topic :: Communications :: Chat
Classifier: License :: OSI Approved :: Apache Software License
Classifier: Programming Language :: Python :: 3.4
Classifier: Programming Language :: Python :: 3.5
